{
    "admin": {
        "host": "0.0.0.0", 
        "port": 1816
    }, 
    "conf_file": "etc/toughradius.json", 
    "database": {
        "backup_path": "/var/toughradius/data", 
        "dbtype": "sqlite", 
        "dburl": "sqlite:////var/toughradius/toughradius.sqlite3", 
        "echo": 0, 
        "pool_recycle": 300, 
        "pool_size": 120
    }, 
    "radiusd": {
        "acct_port": 1813, 
        "auth_port": 1812, 
        "host": "0.0.0.0"
    }, 
    "redis": {
        "host": "127.0.0.1", 
        "passwd": "", 
        "port": 16370
    }, 
    "syslog": {
        "enable": 0, 
        "level": "INFO", 
        "port": 514, 
        "server": "127.0.0.1", 
        "shost": "toughradius_admin"
    }, 
    "system": {
        "debug": 1, 
        "license": "free license", 
        "superrpc": "http://ctlman:ctlroot@127.0.0.1:9002/RPC2", 
        "secret": "CRTCcMB7tfnXU8aXIyfavfuqruvXkNng", 
        "service_url": "http://service.toughstruct.net:9079", 
        "tz": "CST-8"
    }
}